[
  {
    "id": "A-1-B01",
    "file": "images/A-1-B01.png",
    "title": "標準ポーズ 男の子01",
    "category": "標準ポーズ",
    "tags": [
      "男の子",
      "立ち",
      "標準"
    ]
  },
  {
    "id": "A-1-B02",
    "file": "images/A-1-B02.png",
    "title": "標準ポーズ 男の子02",
    "category": "標準ポーズ",
    "tags": [
      "男の子",
      "立ち",
      "標準"
    ]
  },
  {
    "id": "A-1-G01",
    "file": "images/A-1-G01.png",
    "title": "標準ポーズ 女の子01",
    "category": "標準ポーズ",
    "tags": [
      "女の子",
      "立ち",
      "標準"
    ]
  },
  {
    "id": "A-1-G02",
    "file": "images/A-1-G02.png",
    "title": "標準ポーズ 女の子02",
    "category": "標準ポーズ",
    "tags": [
      "女の子",
      "立ち",
      "標準"
    ]
  },
  {
    "id": "A-2-B01",
    "file": "images/A-2-B01.png",
    "title": "標準ポーズ・冬 男の子01",
    "category": "標準ポーズ",
    "tags": [
      "男の子",
      "立ち",
      "冬"
    ]
  },
  {
    "id": "A-2-B02",
    "file": "images/A-2-B02.png",
    "title": "標準ポーズ・冬 男の子02",
    "category": "標準ポーズ",
    "tags": [
      "男の子",
      "立ち",
      "冬"
    ]
  },
  {
    "id": "A-2-G01",
    "file": "images/A-2-G01.png",
    "title": "標準ポーズ・冬 女の子01",
    "category": "標準ポーズ",
    "tags": [
      "女の子",
      "立ち",
      "冬"
    ]
  },
  {
    "id": "A-2-G02",
    "file": "images/A-2-G02.png",
    "title": "標準ポーズ・冬 女の子02",
    "category": "標準ポーズ",
    "tags": [
      "女の子",
      "立ち",
      "冬"
    ]
  },
  {
    "id": "A-3-B01",
    "file": "images/A-3-B01.png",
    "title": "標準ポーズ・冬 男の子03",
    "category": "標準ポーズ",
    "tags": [
      "男の子",
      "立ち",
      "冬"
    ]
  },
  {
    "id": "A-3-B02",
    "file": "images/A-3-B02.png",
    "title": "標準ポーズ・冬 男の子04",
    "category": "標準ポーズ",
    "tags": [
      "男の子",
      "立ち",
      "冬"
    ]
  },
  {
    "id": "A-3-G01",
    "file": "images/A-3-G01.png",
    "title": "標準ポーズ・冬 女の子03",
    "category": "標準ポーズ",
    "tags": [
      "女の子",
      "立ち",
      "冬"
    ]
  },
  {
    "id": "A-3-G02",
    "file": "images/A-3-G02.png",
    "title": "標準ポーズ・冬 女の子04",
    "category": "標準ポーズ",
    "tags": [
      "女の子",
      "立ち",
      "冬"
    ]
  },
  {
    "id": "A-4-B01",
    "file": "images/A-4-B01.png",
    "title": "標準ポーズ・春秋 男の子01",
    "category": "標準ポーズ",
    "tags": [
      "男の子",
      "立ち",
      "春",
      "秋"
    ]
  },
  {
    "id": "A-4-B02",
    "file": "images/A-4-B02.png",
    "title": "標準ポーズ・春秋 男の子02",
    "category": "標準ポーズ",
    "tags": [
      "男の子",
      "立ち",
      "春",
      "秋"
    ]
  },
  {
    "id": "A-4-B03",
    "file": "images/A-4-B03.png",
    "title": "標準ポーズ・春秋 男の子03",
    "category": "標準ポーズ",
    "tags": [
      "男の子",
      "立ち",
      "春",
      "秋"
    ]
  },
  {
    "id": "A-4-G01",
    "file": "images/A-4-G01.png",
    "title": "標準ポーズ・春秋 女の子01",
    "category": "標準ポーズ",
    "tags": [
      "女の子",
      "立ち",
      "春",
      "秋"
    ]
  },
  {
    "id": "A-4-G02",
    "file": "images/A-4-G02.png",
    "title": "標準ポーズ・春秋 女の子02",
    "category": "標準ポーズ",
    "tags": [
      "女の子",
      "立ち",
      "春",
      "秋"
    ]
  },
  {
    "id": "A-4-G03",
    "file": "images/A-4-G03.png",
    "title": "標準ポーズ・春秋 女の子03",
    "category": "標準ポーズ",
    "tags": [
      "女の子",
      "立ち",
      "春",
      "秋"
    ]
  },
  {
    "id": "A-5-B01",
    "file": "images/A-5-B01.png",
    "title": "標準ポーズ・給食 男の子01",
    "category": "標準ポーズ",
    "tags": [
      "男の子",
      "給食"
    ]
  },
  {
    "id": "A-5-B02",
    "file": "images/A-5-B02.png",
    "title": "標準ポーズ・給食 男の子02",
    "category": "標準ポーズ",
    "tags": [
      "男の子",
      "給食"
    ]
  },
  {
    "id": "A-5-G01",
    "file": "images/A-5-G01.png",
    "title": "標準ポーズ・給食 女の子01",
    "category": "標準ポーズ",
    "tags": [
      "女の子",
      "給食"
    ]
  },
  {
    "id": "A-5-G02",
    "file": "images/A-5-G02.png",
    "title": "標準ポーズ・給食 女の子02",
    "category": "標準ポーズ",
    "tags": [
      "女の子",
      "給食"
    ]
  },
  {
    "id": "A-6-B01",
    "file": "images/A-6-B01.png",
    "title": "標準ポーズ・体育 男の子01",
    "category": "標準ポーズ",
    "tags": [
      "男の子",
      "体育"
    ]
  },
  {
    "id": "A-6-B02",
    "file": "images/A-6-B02.png",
    "title": "標準ポーズ・体育 男の子02",
    "category": "標準ポーズ",
    "tags": [
      "男の子",
      "体育"
    ]
  },
  {
    "id": "A-6-G01",
    "file": "images/A-6-G01.png",
    "title": "標準ポーズ・体育 女の子01",
    "category": "標準ポーズ",
    "tags": [
      "女の子",
      "体育"
    ]
  },
  {
    "id": "A-6-G02",
    "file": "images/A-6-G02.png",
    "title": "標準ポーズ・体育 女の子02",
    "category": "標準ポーズ",
    "tags": [
      "女の子",
      "体育"
    ]
  },
  {
    "id": "B-1-B01",
    "file": "images/B-1-B01.png",
    "title": "動きのあるポーズ・冬 男の子01",
    "category": "動きのあるポーズ",
    "tags": [
      "男の子",
      "動き",
      "冬"
    ]
  },
  {
    "id": "B-1-B02",
    "file": "images/B-1-B02.png",
    "title": "動きのあるポーズ・冬 男の子02",
    "category": "動きのあるポーズ",
    "tags": [
      "男の子",
      "動き",
      "冬"
    ]
  },
  {
    "id": "B-1-G01",
    "file": "images/B-1-G01.png",
    "title": "動きのあるポーズ・冬 女の子01",
    "category": "動きのあるポーズ",
    "tags": [
      "女の子",
      "動き",
      "冬"
    ]
  },
  {
    "id": "B-1-G02",
    "file": "images/B-1-G02.png",
    "title": "動きのあるポーズ・冬 女の子02",
    "category": "動きのあるポーズ",
    "tags": [
      "女の子",
      "動き",
      "冬"
    ]
  },
  {
    "id": "B-2-B01",
    "file": "images/B-2-B01.png",
    "title": "動きのあるポーズ・夏 男の子01",
    "category": "動きのあるポーズ",
    "tags": [
      "男の子",
      "動き",
      "夏"
    ]
  },
  {
    "id": "B-2-B02",
    "file": "images/B-2-B02.png",
    "title": "動きのあるポーズ・夏 男の子02",
    "category": "動きのあるポーズ",
    "tags": [
      "男の子",
      "動き",
      "夏"
    ]
  },
  {
    "id": "B-2-G01",
    "file": "images/B-2-G01.png",
    "title": "動きのあるポーズ・夏 女の子01",
    "category": "動きのあるポーズ",
    "tags": [
      "女の子",
      "動き",
      "夏"
    ]
  },
  {
    "id": "B-2-G02",
    "file": "images/B-2-G02.png",
    "title": "動きのあるポーズ・夏 女の子02",
    "category": "動きのあるポーズ",
    "tags": [
      "女の子",
      "動き",
      "夏"
    ]
  },
  {
    "id": "B-3-B01",
    "file": "images/B-3-B01.png",
    "title": "動きのあるポーズ・冬 男の子03",
    "category": "動きのあるポーズ",
    "tags": [
      "男の子",
      "動き",
      "冬"
    ]
  },
  {
    "id": "B-3-G01",
    "file": "images/B-3-G01.png",
    "title": "動きのあるポーズ・冬 女の子03",
    "category": "動きのあるポーズ",
    "tags": [
      "女の子",
      "動き",
      "冬"
    ]
  },
  {
    "id": "B-4-B01",
    "file": "images/B-4-B01.png",
    "title": "動きのあるポーズ・冬 男の子04",
    "category": "動きのあるポーズ",
    "tags": [
      "男の子",
      "動き",
      "冬"
    ]
  },
  {
    "id": "B-4-B02",
    "file": "images/B-4-B02.png",
    "title": "動きのあるポーズ・冬 男の子05",
    "category": "動きのあるポーズ",
    "tags": [
      "男の子",
      "動き",
      "冬"
    ]
  },
  {
    "id": "B-4-G01",
    "file": "images/B-4-G01.png",
    "title": "動きのあるポーズ・冬 女の子04",
    "category": "動きのあるポーズ",
    "tags": [
      "女の子",
      "動き",
      "冬"
    ]
  },
  {
    "id": "B-4-G02",
    "file": "images/B-4-G02.png",
    "title": "動きのあるポーズ・冬 女の子05",
    "category": "動きのあるポーズ",
    "tags": [
      "女の子",
      "動き",
      "冬"
    ]
  },
  {
    "id": "B-5-B01",
    "file": "images/B-5-B01.png",
    "title": "動きのあるポーズ・冬 男の子06",
    "category": "動きのあるポーズ",
    "tags": [
      "男の子",
      "動き",
      "冬"
    ]
  },
  {
    "id": "B-5-B02",
    "file": "images/B-5-B02.png",
    "title": "動きのあるポーズ・冬 男の子07",
    "category": "動きのあるポーズ",
    "tags": [
      "男の子",
      "動き",
      "冬"
    ]
  },
  {
    "id": "B-5-B03",
    "file": "images/B-5-B03.png",
    "title": "動きのあるポーズ・冬 男の子08",
    "category": "動きのあるポーズ",
    "tags": [
      "男の子",
      "動き",
      "冬"
    ]
  },
  {
    "id": "B-5-B04",
    "file": "images/B-5-B04.png",
    "title": "動きのあるポーズ・冬 男の子09",
    "category": "動きのあるポーズ",
    "tags": [
      "男の子",
      "動き",
      "冬"
    ]
  },
  {
    "id": "B-5-B05",
    "file": "images/B-5-B05.png",
    "title": "動きのあるポーズ・冬 男の子10",
    "category": "動きのあるポーズ",
    "tags": [
      "男の子",
      "動き",
      "冬"
    ]
  },
  {
    "id": "B-5-B06",
    "file": "images/B-5-B06.png",
    "title": "動きのあるポーズ・冬 男の子11",
    "category": "動きのあるポーズ",
    "tags": [
      "男の子",
      "動き",
      "冬"
    ]
  },
  {
    "id": "B-5-B07",
    "file": "images/B-5-B07.png",
    "title": "動きのあるポーズ・夏 男の子03",
    "category": "動きのあるポーズ",
    "tags": [
      "男の子",
      "動き",
      "夏"
    ]
  },
  {
    "id": "B-5-G01",
    "file": "images/B-5-G01.png",
    "title": "動きのあるポーズ・冬 女の子06",
    "category": "動きのあるポーズ",
    "tags": [
      "女の子",
      "動き",
      "冬"
    ]
  },
  {
    "id": "B-5-G02",
    "file": "images/B-5-G02.png",
    "title": "動きのあるポーズ・冬 女の子07",
    "category": "動きのあるポーズ",
    "tags": [
      "女の子",
      "動き",
      "冬"
    ]
  },
  {
    "id": "B-5-G03",
    "file": "images/B-5-G03.png",
    "title": "動きのあるポーズ・冬 女の子08",
    "category": "動きのあるポーズ",
    "tags": [
      "女の子",
      "動き",
      "冬"
    ]
  },
  {
    "id": "B-5-G04",
    "file": "images/B-5-G04.png",
    "title": "動きのあるポーズ・冬 女の子09",
    "category": "動きのあるポーズ",
    "tags": [
      "女の子",
      "動き",
      "冬"
    ]
  },
  {
    "id": "B-5-G05",
    "file": "images/B-5-G05.png",
    "title": "動きのあるポーズ・冬 女の子10",
    "category": "動きのあるポーズ",
    "tags": [
      "女の子",
      "動き",
      "冬"
    ]
  },
  {
    "id": "B-5-G06",
    "file": "images/B-5-G06.png",
    "title": "動きのあるポーズ・冬 女の子11",
    "category": "動きのあるポーズ",
    "tags": [
      "女の子",
      "動き",
      "冬"
    ]
  },
  {
    "id": "B-5-G07",
    "file": "images/B-5-G07.png",
    "title": "動きのあるポーズ・夏 女の子03",
    "category": "動きのあるポーズ",
    "tags": [
      "女の子",
      "動き",
      "夏"
    ]
  },
  {
    "id": "B-6-T01",
    "file": "images/B-6-T01.png",
    "title": "動きのあるポーズ・冬 ふたり01",
    "category": "動きのあるポーズ",
    "tags": [
      "ふたり",
      "動き",
      "冬"
    ]
  },
  {
    "id": "B-6-T02",
    "file": "images/B-6-T02.png",
    "title": "動きのあるポーズ・夏 ふたり02",
    "category": "動きのあるポーズ",
    "tags": [
      "ふたり",
      "動き",
      "夏"
    ]
  },
  {
    "id": "B-6-T03",
    "file": "images/B-6-T03.png",
    "title": "動きのあるポーズ・体育 ふたり03",
    "category": "動きのあるポーズ",
    "tags": [
      "ふたり",
      "動き",
      "体育"
    ]
  },
  {
    "id": "C-1-B01",
    "file": "images/C-1-B01.png",
    "title": "学校行事・春秋 男の子01",
    "category": "学校行事",
    "tags": [
      "男の子",
      "春",
      "秋"
    ]
  },
  {
    "id": "C-1-B02",
    "file": "images/C-1-B02.png",
    "title": "学校行事・春秋 男の子02",
    "category": "学校行事",
    "tags": [
      "男の子",
      "春",
      "秋"
    ]
  },
  {
    "id": "C-1-B03",
    "file": "images/C-1-B03.png",
    "title": "学校行事・春秋 男の子03",
    "category": "学校行事",
    "tags": [
      "男の子",
      "春",
      "秋"
    ]
  },
  {
    "id": "C-1-G01",
    "file": "images/C-1-G01.png",
    "title": "学校行事・春秋 女の子01",
    "category": "学校行事",
    "tags": [
      "女の子",
      "春",
      "秋"
    ]
  },
  {
    "id": "C-1-G02",
    "file": "images/C-1-G02.png",
    "title": "学校行事・春秋 女の子02",
    "category": "学校行事",
    "tags": [
      "女の子",
      "春",
      "秋"
    ]
  },
  {
    "id": "C-1-G03",
    "file": "images/C-1-G03.png",
    "title": "学校行事・春秋 女の子03",
    "category": "学校行事",
    "tags": [
      "女の子",
      "春",
      "秋"
    ]
  },
  {
    "id": "C-2-B01",
    "file": "images/C-2-B01.png",
    "title": "学校行事・春秋 男の子04",
    "category": "学校行事",
    "tags": [
      "男の子",
      "春",
      "秋"
    ]
  },
  {
    "id": "C-2-B02",
    "file": "images/C-2-B02.png",
    "title": "学校行事・春秋 男の子05",
    "category": "学校行事",
    "tags": [
      "男の子",
      "春",
      "秋"
    ]
  },
  {
    "id": "C-2-G01",
    "file": "images/C-2-G01.png",
    "title": "学校行事・春秋 女の子04",
    "category": "学校行事",
    "tags": [
      "女の子",
      "春",
      "秋"
    ]
  },
  {
    "id": "C-2-G02",
    "file": "images/C-2-G02.png",
    "title": "学校行事・春秋 女の子05",
    "category": "学校行事",
    "tags": [
      "女の子",
      "春",
      "秋"
    ]
  },
  {
    "id": "C-3-B01",
    "file": "images/C-3-B01.png",
    "title": "学校行事・給食 男の子01",
    "category": "学校行事",
    "tags": [
      "男の子",
      "給食"
    ]
  },
  {
    "id": "C-3-B02",
    "file": "images/C-3-B02.png",
    "title": "学校行事・給食 男の子02",
    "category": "学校行事",
    "tags": [
      "男の子",
      "給食"
    ]
  },
  {
    "id": "C-3-G01",
    "file": "images/C-3-G01.png",
    "title": "学校行事・給食 女の子01",
    "category": "学校行事",
    "tags": [
      "女の子",
      "給食"
    ]
  },
  {
    "id": "C-3-G02",
    "file": "images/C-3-G02.png",
    "title": "学校行事・給食 女の子02",
    "category": "学校行事",
    "tags": [
      "女の子",
      "給食"
    ]
  },
  {
    "id": "C-4-B01",
    "file": "images/C-4-B01.png",
    "title": "学校行事・春秋 男の子06",
    "category": "学校行事",
    "tags": [
      "男の子",
      "春",
      "秋"
    ]
  },
  {
    "id": "C-4-B02",
    "file": "images/C-4-B02.png",
    "title": "学校行事・春秋 男の子07",
    "category": "学校行事",
    "tags": [
      "男の子",
      "春",
      "秋"
    ]
  },
  {
    "id": "C-4-G01",
    "file": "images/C-4-G01.png",
    "title": "学校行事・春秋 女の子06",
    "category": "学校行事",
    "tags": [
      "女の子",
      "春",
      "秋"
    ]
  },
  {
    "id": "C-4-G02",
    "file": "images/C-4-G02.png",
    "title": "学校行事・春秋 女の子07",
    "category": "学校行事",
    "tags": [
      "女の子",
      "春",
      "秋"
    ]
  },
  {
    "id": "C-5-B01",
    "file": "images/C-5-B01.png",
    "title": "学校行事・春秋 男の子08",
    "category": "学校行事",
    "tags": [
      "男の子",
      "春",
      "秋"
    ]
  },
  {
    "id": "C-5-B02",
    "file": "images/C-5-B02.png",
    "title": "学校行事・春秋 男の子09",
    "category": "学校行事",
    "tags": [
      "男の子",
      "春",
      "秋"
    ]
  },
  {
    "id": "C-5-G01",
    "file": "images/C-5-G01.png",
    "title": "学校行事・春秋 女の子08",
    "category": "学校行事",
    "tags": [
      "女の子",
      "春",
      "秋"
    ]
  },
  {
    "id": "C-5-G02",
    "file": "images/C-5-G02.png",
    "title": "学校行事・春秋 女の子09",
    "category": "学校行事",
    "tags": [
      "女の子",
      "春",
      "秋"
    ]
  },
  {
    "id": "C-6-B01",
    "file": "images/C-6-B01.png",
    "title": "学校行事・体育 男の子01",
    "category": "学校行事",
    "tags": [
      "男の子",
      "体育"
    ]
  },
  {
    "id": "C-6-B02",
    "file": "images/C-6-B02.png",
    "title": "学校行事・体育 男の子02",
    "category": "学校行事",
    "tags": [
      "男の子",
      "体育"
    ]
  },
  {
    "id": "C-6-B03",
    "file": "images/C-6-B03.png",
    "title": "学校行事・体育 男の子03",
    "category": "学校行事",
    "tags": [
      "男の子",
      "体育"
    ]
  },
  {
    "id": "C-6-G01",
    "file": "images/C-6-G01.png",
    "title": "学校行事・体育 女の子01",
    "category": "学校行事",
    "tags": [
      "女の子",
      "体育"
    ]
  },
  {
    "id": "C-6-G02",
    "file": "images/C-6-G02.png",
    "title": "学校行事・体育 女の子02",
    "category": "学校行事",
    "tags": [
      "女の子",
      "体育"
    ]
  },
  {
    "id": "C-6-G03",
    "file": "images/C-6-G03.png",
    "title": "学校行事・体育 女の子03",
    "category": "学校行事",
    "tags": [
      "女の子",
      "体育"
    ]
  },
  {
    "id": "D-1-B01",
    "file": "images/D-1-B01.png",
    "title": "テーマ・春 男の子01",
    "category": "テーマ",
    "tags": [
      "男の子",
      "春"
    ]
  },
  {
    "id": "D-1-G01",
    "file": "images/D-1-G01.png",
    "title": "テーマ・春 女の子01",
    "category": "テーマ",
    "tags": [
      "女の子",
      "春"
    ]
  },
  {
    "id": "D-1-T01",
    "file": "images/D-1-T01.png",
    "title": "テーマ・春 ふたり01",
    "category": "テーマ",
    "tags": [
      "ふたり",
      "春"
    ]
  },
  {
    "id": "D-2-S01",
    "file": "images/D-2-S01.png",
    "title": "テーマ その他01",
    "category": "テーマ",
    "tags": [
      "その他"
    ]
  },
  {
    "id": "D-2-S02",
    "file": "images/D-2-S02.png",
    "title": "テーマ その他02",
    "category": "テーマ",
    "tags": [
      "その他"
    ]
  },
  {
    "id": "D-3-B01",
    "file": "images/D-3-B01.png",
    "title": "テーマ・冬 男の子01",
    "category": "テーマ",
    "tags": [
      "男の子",
      "冬"
    ]
  },
  {
    "id": "D-3-B02",
    "file": "images/D-3-B02.png",
    "title": "テーマ・冬 男の子02",
    "category": "テーマ",
    "tags": [
      "男の子",
      "冬"
    ]
  },
  {
    "id": "D-3-G01",
    "file": "images/D-3-G01.png",
    "title": "テーマ・冬 女の子01",
    "category": "テーマ",
    "tags": [
      "女の子",
      "冬"
    ]
  },
  {
    "id": "D-3-G02",
    "file": "images/D-3-G02.png",
    "title": "テーマ・冬 女の子02",
    "category": "テーマ",
    "tags": [
      "女の子",
      "冬"
    ]
  },
  {
    "id": "D-4-B01",
    "file": "images/D-4-B01.png",
    "title": "テーマ 男の子01",
    "category": "テーマ",
    "tags": [
      "男の子"
    ]
  },
  {
    "id": "D-4-B02",
    "file": "images/D-4-B02.png",
    "title": "テーマ 男の子02",
    "category": "テーマ",
    "tags": [
      "男の子"
    ]
  },
  {
    "id": "D-4-B03",
    "file": "images/D-4-B03.png",
    "title": "テーマ 男の子03",
    "category": "テーマ",
    "tags": [
      "男の子"
    ]
  },
  {
    "id": "D-4-B04",
    "file": "images/D-4-B04.png",
    "title": "テーマ 男の子04",
    "category": "テーマ",
    "tags": [
      "男の子"
    ]
  },
  {
    "id": "D-4-B51",
    "file": "images/D-4-B51.png",
    "title": "テーマ 男の子 線画01",
    "category": "テーマ",
    "tags": [
      "男の子",
      "線画"
    ]
  },
  {
    "id": "D-4-B52",
    "file": "images/D-4-B52.png",
    "title": "テーマ 男の子 線画02",
    "category": "テーマ",
    "tags": [
      "男の子",
      "線画"
    ]
  },
  {
    "id": "D-4-B53",
    "file": "images/D-4-B53.png",
    "title": "テーマ 男の子 線画03",
    "category": "テーマ",
    "tags": [
      "男の子",
      "線画"
    ]
  },
  {
    "id": "D-4-B54",
    "file": "images/D-4-B54.png",
    "title": "テーマ 男の子 線画04",
    "category": "テーマ",
    "tags": [
      "男の子",
      "線画"
    ]
  },
  {
    "id": "D-5-B01",
    "file": "images/D-5-B01.png",
    "title": "テーマ 男の子05",
    "category": "テーマ",
    "tags": [
      "男の子"
    ]
  },
  {
    "id": "D-5-B02",
    "file": "images/D-5-B02.png",
    "title": "テーマ 男の子06",
    "category": "テーマ",
    "tags": [
      "男の子"
    ]
  },
  {
    "id": "D-5-B03",
    "file": "images/D-5-B03.png",
    "title": "テーマ 男の子07",
    "category": "テーマ",
    "tags": [
      "男の子"
    ]
  },
  {
    "id": "D-5-B04",
    "file": "images/D-5-B04.png",
    "title": "テーマ 男の子08",
    "category": "テーマ",
    "tags": [
      "男の子"
    ]
  },
  {
    "id": "D-5-B05",
    "file": "images/D-5-B05.png",
    "title": "テーマ 男の子09",
    "category": "テーマ",
    "tags": [
      "男の子"
    ]
  },
  {
    "id": "D-5-B06",
    "file": "images/D-5-B06.png",
    "title": "テーマ 男の子10",
    "category": "テーマ",
    "tags": [
      "男の子"
    ]
  },
  {
    "id": "D-5-B21",
    "file": "images/D-5-B21.png",
    "title": "テーマ 男の子 別バージョン01",
    "category": "テーマ",
    "tags": [
      "男の子",
      "別バージョン"
    ]
  },
  {
    "id": "D-5-B22",
    "file": "images/D-5-B22.png",
    "title": "テーマ 男の子 別バージョン02",
    "category": "テーマ",
    "tags": [
      "男の子",
      "別バージョン"
    ]
  },
  {
    "id": "D-5-B23",
    "file": "images/D-5-B23.png",
    "title": "テーマ 男の子 別バージョン03",
    "category": "テーマ",
    "tags": [
      "男の子",
      "別バージョン"
    ]
  },
  {
    "id": "D-5-B24",
    "file": "images/D-5-B24.png",
    "title": "テーマ 男の子 別バージョン04",
    "category": "テーマ",
    "tags": [
      "男の子",
      "別バージョン"
    ]
  },
  {
    "id": "D-5-B25",
    "file": "images/D-5-B25.png",
    "title": "テーマ 男の子 別バージョン05",
    "category": "テーマ",
    "tags": [
      "男の子",
      "別バージョン"
    ]
  },
  {
    "id": "D-5-B26",
    "file": "images/D-5-B26.png",
    "title": "テーマ 男の子 別バージョン06",
    "category": "テーマ",
    "tags": [
      "男の子",
      "別バージョン"
    ]
  },
  {
    "id": "D-5-B51",
    "file": "images/D-5-B51.png",
    "title": "テーマ 男の子 線画05",
    "category": "テーマ",
    "tags": [
      "男の子",
      "線画"
    ]
  },
  {
    "id": "D-5-B52",
    "file": "images/D-5-B52.png",
    "title": "テーマ 男の子 線画06",
    "category": "テーマ",
    "tags": [
      "男の子",
      "線画"
    ]
  },
  {
    "id": "D-5-B53",
    "file": "images/D-5-B53.png",
    "title": "テーマ 男の子 線画07",
    "category": "テーマ",
    "tags": [
      "男の子",
      "線画"
    ]
  },
  {
    "id": "D-5-B54",
    "file": "images/D-5-B54.png",
    "title": "テーマ 男の子 線画08",
    "category": "テーマ",
    "tags": [
      "男の子",
      "線画"
    ]
  },
  {
    "id": "D-5-B55",
    "file": "images/D-5-B55.png",
    "title": "テーマ 男の子 線画09",
    "category": "テーマ",
    "tags": [
      "男の子",
      "線画"
    ]
  },
  {
    "id": "D-5-B56",
    "file": "images/D-5-B56.png",
    "title": "テーマ 男の子 線画10",
    "category": "テーマ",
    "tags": [
      "男の子",
      "線画"
    ]
  }
]
